{
    "pages": {
    "1": {
      "items": [
        {
          "name": "Pokeball",
          "cost": 200,
          "OnlyBuyOne": false,
          "CanBeSold": true,
          "QueryIndex": 1
        },
        {
          "name": "Greatball",
          "cost": 500,
          "OnlyBuyOne": false,
          "CanBeSold": true,
          "QueryIndex": 2
        },
        {
          "name": "Ultraball",
          "cost": 1500,
          "OnlyBuyOne": false,
          "CanBeSold": true,
          "QueryIndex": 3
        },
        {
          "name": "Red Card",
          "cost": 10000,
          "OnlyBuyOne": false,
          "CanBeSold": true,
          "emoji": "<:redcard:922999500317007944>",
          "QueryIndex": 4
        },
        {
          "name": "Eviolite",
          "cost": 15000,
          "OnlyBuyOne": false,
          "CanBeSold": true,
          "emoji": "<:eviolite:922999566884802561>",
          "QueryIndex": 5
        },
        {
          "name": "Amulet Coin",
          "cost": 150000,
          "OnlyBuyOne": true,
          "CanBeSold": false,
          "emoji": "<:Dream_Amulet_Coin_Sprite:858192440786944020>",
          "QueryIndex": 6
        },
        {
          "name": "Rare Candy",
          "cost": 150000,
          "OnlyBuyOne": true,
          "CanBeSold": false,
          "emoji": "<:Dream_Rare_Candy_Sprite:858192390757416970>",
          "QueryIndex": 7
        }
      ]
    },
    "2": {
      "items": [
        {
          "name": "Claw Fossil",
          "emoji": "<:clawfossil:934937792428003429>",
          "cost": 5000,
          "CanBeSold": false,
          "hidden": true,
          "QueryIndex": 30
        },
        {
          "name": "Dome Fossil",
          "emoji": "<:domefossil:934937754461147186>",
          "cost": 5000,
          "CanBeSold": false,
          "hidden": true,
          "QueryIndex": 31
        },
        {
          "name": "Skull Fossil",
          "emoji": "<:skullfossil:934937916646502410>",
          "cost": 5000,
          "CanBeSold": false,
          "hidden": true,
          "QueryIndex": 32
        },
        {
          "name": "Root Fossil",
          "emoji": "<:rootfossil:934937934350663711>",
          "cost": 5000,
          "CanBeSold": false,
          "hidden": true,
          "QueryIndex": 33
        },
        {
          "name": "Helix Fossil",
          "emoji": "<:helixfossil:934937778553253889>",
          "cost": 5000,
          "CanBeSold": false,
          "hidden": true,
          "QueryIndex": 34
        },
        {
          "name": "Blue Sphere",
          "emoji": "<:bluesphere:934937848627478598>",
          "cost": 1,
          "CanBeSold": false,
          "hidden": true,
          "QueryIndex": 35
        },
        {
          "name": "Green Sphere",
          "emoji": "<:greensphere:934937857964011540>",
          "cost": 1,
          "CanBeSold": false,
          "hidden": true,
          "QueryIndex": 36
        },
        {
          "name": "Red Sphere",
          "emoji": "<:redsphere:934937890289504336>",
          "cost": 1,
          "CanBeSold": false,
          "hidden": true,
          "QueryIndex": 37
        },
        {
          "name": "Prism Sphere",
          "emoji": "<:prismsphere:934937830629716060>",
          "cost": 1,
          "CanBeSold": false,
          "hidden": true,
          "QueryIndex": 38
        },
        {
          "name": "Pale Sphere",
          "emoji": "<:palesphere:934937877488467978>",
          "cost": 1,
          "CanBeSold": true,
          "hidden": true,
          "QueryIndex": 39
        }
      ]
    }
  }
}
